{
    "$schema": "http://json-schema.org/draft-04/schema#",
    "properties": {
        "ChatterExtension": {
            "required": [
                "compositionComponent",
                "description",
                "extensionName",
                "icon",
                "masterLabel",
                "renderComponent",
                "type"
            ],
            "allOf": [
                {
                    "$ref": "https://s3-us-west-2.amazonaws.com/djcarroll/schemas/modedSchema/MetadataSchema.json"
                },
                {
                    "type": "object",
                    "title": "ChatterExtension",
                    "properties": {
                        "compositionComponent": {
                            "title": "compositionComponent",
                            "allOf": [
                                {
                                    "$ref": "http://www.jsonix.org/jsonschemas/w3c/2001/XMLSchema.jsonschema#/definitions/string"
                                }
                            ],
                            "propertyType": "element",
                            "elementName": {
                                "localPart": "compositionComponent",
                                "namespaceURI": "http://soap.sforce.com/2006/04/metadata"
                            }
                        },
                        "description": {
                            "title": "description",
                            "allOf": [
                                {
                                    "$ref": "http://www.jsonix.org/jsonschemas/w3c/2001/XMLSchema.jsonschema#/definitions/string"
                                }
                            ],
                            "propertyType": "element",
                            "elementName": {
                                "localPart": "description",
                                "namespaceURI": "http://soap.sforce.com/2006/04/metadata"
                            }
                        },
                        "extensionName": {
                            "title": "extensionName",
                            "allOf": [
                                {
                                    "$ref": "http://www.jsonix.org/jsonschemas/w3c/2001/XMLSchema.jsonschema#/definitions/string"
                                }
                            ],
                            "propertyType": "element",
                            "elementName": {
                                "localPart": "extensionName",
                                "namespaceURI": "http://soap.sforce.com/2006/04/metadata"
                            }
                        },
                        "headerText": {
                            "title": "headerText",
                            "allOf": [
                                {
                                    "$ref": "http://www.jsonix.org/jsonschemas/w3c/2001/XMLSchema.jsonschema#/definitions/string"
                                }
                            ],
                            "propertyType": "element",
                            "elementName": {
                                "localPart": "headerText",
                                "namespaceURI": "http://soap.sforce.com/2006/04/metadata"
                            }
                        },
                        "hoverText": {
                            "title": "hoverText",
                            "allOf": [
                                {
                                    "$ref": "http://www.jsonix.org/jsonschemas/w3c/2001/XMLSchema.jsonschema#/definitions/string"
                                }
                            ],
                            "propertyType": "element",
                            "elementName": {
                                "localPart": "hoverText",
                                "namespaceURI": "http://soap.sforce.com/2006/04/metadata"
                            }
                        },
                        "icon": {
                            "title": "icon",
                            "allOf": [
                                {
                                    "$ref": "http://www.jsonix.org/jsonschemas/w3c/2001/XMLSchema.jsonschema#/definitions/string"
                                }
                            ],
                            "propertyType": "element",
                            "elementName": {
                                "localPart": "icon",
                                "namespaceURI": "http://soap.sforce.com/2006/04/metadata"
                            }
                        },
                        "isProtected": {
                            "title": "isProtected",
                            "allOf": [
                                {
                                    "$ref": "http://www.jsonix.org/jsonschemas/w3c/2001/XMLSchema.jsonschema#/definitions/boolean"
                                }
                            ],
                            "propertyType": "element",
                            "elementName": {
                                "localPart": "isProtected",
                                "namespaceURI": "http://soap.sforce.com/2006/04/metadata"
                            }
                        },
                        "masterLabel": {
                            "title": "masterLabel",
                            "allOf": [
                                {
                                    "$ref": "http://www.jsonix.org/jsonschemas/w3c/2001/XMLSchema.jsonschema#/definitions/string"
                                }
                            ],
                            "propertyType": "element",
                            "elementName": {
                                "localPart": "masterLabel",
                                "namespaceURI": "http://soap.sforce.com/2006/04/metadata"
                            }
                        },
                        "renderComponent": {
                            "title": "renderComponent",
                            "allOf": [
                                {
                                    "$ref": "http://www.jsonix.org/jsonschemas/w3c/2001/XMLSchema.jsonschema#/definitions/string"
                                }
                            ],
                            "propertyType": "element",
                            "elementName": {
                                "localPart": "renderComponent",
                                "namespaceURI": "http://soap.sforce.com/2006/04/metadata"
                            }
                        },
                        "type": {
                            "title": "type",
                            "allOf": [
                                {
                                    "$ref": "https://s3-us-west-2.amazonaws.com/djcarroll/schemas/modedSchema/ChatterExtensionTypeSchema.json"
                                }
                            ],
                            "propertyType": "element",
                            "elementName": {
                                "localPart": "type",
                                "namespaceURI": "http://soap.sforce.com/2006/04/metadata"
                            }
                        }
                    }
                }
            ],
            "typeType": "classInfo",
            "typeName": {
                "localPart": "ChatterExtension",
                "namespaceURI": "http://soap.sforce.com/2006/04/metadata"
            },
            "propertiesOrder": [
                "compositionComponent",
                "description",
                "extensionName",
                "headerText",
                "hoverText",
                "icon",
                "isProtected",
                "masterLabel",
                "renderComponent",
                "type"
            ]
        }
    }
}