{
    "$schema": "http://json-schema.org/draft-04/schema#",
    "properties": {
        "Role": {
            "allOf": [
                {
                    "$ref": "https://s3-us-west-2.amazonaws.com/djcarroll/schemas/modedSchema/RoleOrTerritorySchema.json"
                },
                {
                    "type": "object",
                    "title": "Role",
                    "properties": {
                        "parentRole": {
                            "title": "parentRole",
                            "allOf": [
                                {
                                    "$ref": "http://www.jsonix.org/jsonschemas/w3c/2001/XMLSchema.jsonschema#/definitions/string"
                                }
                            ],
                            "propertyType": "element",
                            "elementName": {
                                "localPart": "parentRole",
                                "namespaceURI": "http://soap.sforce.com/2006/04/metadata"
                            }
                        }
                    }
                }
            ],
            "typeType": "classInfo",
            "typeName": {
                "localPart": "Role",
                "namespaceURI": "http://soap.sforce.com/2006/04/metadata"
            },
            "propertiesOrder": [
                "parentRole"
            ]
        }
    }
}