{
    "$schema": "http://json-schema.org/draft-04/schema#",
    "properties": {
        "AppPreferences": {
            "type": "object",
            "title": "AppPreferences",
            "required": [
                "enableCustomizeMyTabs",
                "enableKeyboardShortcuts",
                "enableListViewHover",
                "enableListViewReskin",
                "enableMultiMonitorComponents",
                "enablePinTabs",
                "enableTabHover",
                "enableTabLimits",
                "saveUserSessions"
            ],
            "properties": {
                "enableCustomizeMyTabs": {
                    "title": "enableCustomizeMyTabs",
                    "allOf": [
                        {
                            "$ref": "http://www.jsonix.org/jsonschemas/w3c/2001/XMLSchema.jsonschema#/definitions/boolean"
                        }
                    ],
                    "propertyType": "element",
                    "elementName": {
                        "localPart": "enableCustomizeMyTabs",
                        "namespaceURI": "http://soap.sforce.com/2006/04/metadata"
                    }
                },
                "enableKeyboardShortcuts": {
                    "title": "enableKeyboardShortcuts",
                    "allOf": [
                        {
                            "$ref": "http://www.jsonix.org/jsonschemas/w3c/2001/XMLSchema.jsonschema#/definitions/boolean"
                        }
                    ],
                    "propertyType": "element",
                    "elementName": {
                        "localPart": "enableKeyboardShortcuts",
                        "namespaceURI": "http://soap.sforce.com/2006/04/metadata"
                    }
                },
                "enableListViewHover": {
                    "title": "enableListViewHover",
                    "allOf": [
                        {
                            "$ref": "http://www.jsonix.org/jsonschemas/w3c/2001/XMLSchema.jsonschema#/definitions/boolean"
                        }
                    ],
                    "propertyType": "element",
                    "elementName": {
                        "localPart": "enableListViewHover",
                        "namespaceURI": "http://soap.sforce.com/2006/04/metadata"
                    }
                },
                "enableListViewReskin": {
                    "title": "enableListViewReskin",
                    "allOf": [
                        {
                            "$ref": "http://www.jsonix.org/jsonschemas/w3c/2001/XMLSchema.jsonschema#/definitions/boolean"
                        }
                    ],
                    "propertyType": "element",
                    "elementName": {
                        "localPart": "enableListViewReskin",
                        "namespaceURI": "http://soap.sforce.com/2006/04/metadata"
                    }
                },
                "enableMultiMonitorComponents": {
                    "title": "enableMultiMonitorComponents",
                    "allOf": [
                        {
                            "$ref": "http://www.jsonix.org/jsonschemas/w3c/2001/XMLSchema.jsonschema#/definitions/boolean"
                        }
                    ],
                    "propertyType": "element",
                    "elementName": {
                        "localPart": "enableMultiMonitorComponents",
                        "namespaceURI": "http://soap.sforce.com/2006/04/metadata"
                    }
                },
                "enablePinTabs": {
                    "title": "enablePinTabs",
                    "allOf": [
                        {
                            "$ref": "http://www.jsonix.org/jsonschemas/w3c/2001/XMLSchema.jsonschema#/definitions/boolean"
                        }
                    ],
                    "propertyType": "element",
                    "elementName": {
                        "localPart": "enablePinTabs",
                        "namespaceURI": "http://soap.sforce.com/2006/04/metadata"
                    }
                },
                "enableTabHover": {
                    "title": "enableTabHover",
                    "allOf": [
                        {
                            "$ref": "http://www.jsonix.org/jsonschemas/w3c/2001/XMLSchema.jsonschema#/definitions/boolean"
                        }
                    ],
                    "propertyType": "element",
                    "elementName": {
                        "localPart": "enableTabHover",
                        "namespaceURI": "http://soap.sforce.com/2006/04/metadata"
                    }
                },
                "enableTabLimits": {
                    "title": "enableTabLimits",
                    "allOf": [
                        {
                            "$ref": "http://www.jsonix.org/jsonschemas/w3c/2001/XMLSchema.jsonschema#/definitions/boolean"
                        }
                    ],
                    "propertyType": "element",
                    "elementName": {
                        "localPart": "enableTabLimits",
                        "namespaceURI": "http://soap.sforce.com/2006/04/metadata"
                    }
                },
                "saveUserSessions": {
                    "title": "saveUserSessions",
                    "allOf": [
                        {
                            "$ref": "http://www.jsonix.org/jsonschemas/w3c/2001/XMLSchema.jsonschema#/definitions/boolean"
                        }
                    ],
                    "propertyType": "element",
                    "elementName": {
                        "localPart": "saveUserSessions",
                        "namespaceURI": "http://soap.sforce.com/2006/04/metadata"
                    }
                }
            },
            "typeType": "classInfo",
            "typeName": {
                "localPart": "AppPreferences",
                "namespaceURI": "http://soap.sforce.com/2006/04/metadata"
            },
            "propertiesOrder": [
                "enableCustomizeMyTabs",
                "enableKeyboardShortcuts",
                "enableListViewHover",
                "enableListViewReskin",
                "enableMultiMonitorComponents",
                "enablePinTabs",
                "enableTabHover",
                "enableTabLimits",
                "saveUserSessions"
            ]
        }
    }
}