{
    "$schema": "http://json-schema.org/draft-04/schema#",
    "properties": {
        "QuickActionLayoutItem": {
            "type": "object",
            "title": "QuickActionLayoutItem",
            "properties": {
                "emptySpace": {
                    "title": "emptySpace",
                    "allOf": [
                        {
                            "$ref": "http://www.jsonix.org/jsonschemas/w3c/2001/XMLSchema.jsonschema#/definitions/boolean"
                        }
                    ],
                    "propertyType": "element",
                    "elementName": {
                        "localPart": "emptySpace",
                        "namespaceURI": "http://soap.sforce.com/2006/04/metadata"
                    }
                },
                "field": {
                    "title": "field",
                    "allOf": [
                        {
                            "$ref": "http://www.jsonix.org/jsonschemas/w3c/2001/XMLSchema.jsonschema#/definitions/string"
                        }
                    ],
                    "propertyType": "element",
                    "elementName": {
                        "localPart": "field",
                        "namespaceURI": "http://soap.sforce.com/2006/04/metadata"
                    }
                },
                "uiBehavior": {
                    "title": "uiBehavior",
                    "allOf": [
                        {
                            "$ref": "https://s3-us-west-2.amazonaws.com/djcarroll/schemas/modedSchema/UiBehaviorSchema.json"
                        }
                    ],
                    "propertyType": "element",
                    "elementName": {
                        "localPart": "uiBehavior",
                        "namespaceURI": "http://soap.sforce.com/2006/04/metadata"
                    }
                }
            },
            "typeType": "classInfo",
            "typeName": {
                "localPart": "QuickActionLayoutItem",
                "namespaceURI": "http://soap.sforce.com/2006/04/metadata"
            },
            "propertiesOrder": [
                "emptySpace",
                "field",
                "uiBehavior"
            ]
        }
    }
}