{
    "$schema": "http://json-schema.org/draft-04/schema#",
    "properties": {
        "ReportBucketFieldSourceValue": {
            "type": "object",
            "title": "ReportBucketFieldSourceValue",
            "properties": {
                "from": {
                    "title": "from",
                    "allOf": [
                        {
                            "$ref": "http://www.jsonix.org/jsonschemas/w3c/2001/XMLSchema.jsonschema#/definitions/string"
                        }
                    ],
                    "propertyType": "element",
                    "elementName": {
                        "localPart": "from",
                        "namespaceURI": "http://soap.sforce.com/2006/04/metadata"
                    }
                },
                "sourceValue": {
                    "title": "sourceValue",
                    "allOf": [
                        {
                            "$ref": "http://www.jsonix.org/jsonschemas/w3c/2001/XMLSchema.jsonschema#/definitions/string"
                        }
                    ],
                    "propertyType": "element",
                    "elementName": {
                        "localPart": "sourceValue",
                        "namespaceURI": "http://soap.sforce.com/2006/04/metadata"
                    }
                },
                "to": {
                    "title": "to",
                    "allOf": [
                        {
                            "$ref": "http://www.jsonix.org/jsonschemas/w3c/2001/XMLSchema.jsonschema#/definitions/string"
                        }
                    ],
                    "propertyType": "element",
                    "elementName": {
                        "localPart": "to",
                        "namespaceURI": "http://soap.sforce.com/2006/04/metadata"
                    }
                }
            },
            "typeType": "classInfo",
            "typeName": {
                "localPart": "ReportBucketFieldSourceValue",
                "namespaceURI": "http://soap.sforce.com/2006/04/metadata"
            },
            "propertiesOrder": [
                "from",
                "sourceValue",
                "to"
            ]
        }
    }
}